{"title":"뉴스페퍼민트","url":"https://newspeppermint.com/","favicon":"https://newspeppermint.com/favicon.ico","elements":[{"title":"[필진 칼럼] 코로나 시대 넛지의 한계","contents":"2022년 6월 29일","link":"https://newspeppermint.com/2022/06/28/npc_nudgecovid/","retrieved":1656457726620},{"title":"[필진 칼럼] 대법관 배우자가 극우 음모론자라면 어떡하나","contents":"2022년 6월 28일","link":"https://newspeppermint.com/2022/06/27/npc_ginnithomas/","retrieved":1656371341355},{"title":"[필진 칼럼] 대학 입시에 시험이 필요할까? MIT와 캘리포니아 주립대학의 정반대 행보","contents":"2022년 6월 27일","link":"https://newspeppermint.com/2022/06/26/npc_collegeadmissiontest/","retrieved":1656284909903},{"title":"[필진 칼럼] 미국 극우파와 푸틴, 다시 쓰는 이념 지형","contents":"2022년 6월 24일","link":"https://newspeppermint.com/2022/06/23/npc_usfarrightputin/","retrieved":1656025741862},{"title":"[필진 칼럼] 침략국 러시아 제재에 동참한 빅테크 기업들","contents":"2022년 6월 23일","link":"https://newspeppermint.com/2022/06/22/npc_russiawarbigtech/","retrieved":1655939372698},{"title":"[필진 칼럼] 인간만이 기하학을 이해할 수 있을까요?","contents":"2022년 6월 22일","link":"https://newspeppermint.com/2022/06/21/npc_geometryanimal/","retrieved":1655852958849},{"title":"[필진 칼럼] 코로나19 백신과 월경 불순, 부작용과 가짜뉴스","contents":"2022년 6월 21일","link":"https://newspeppermint.com/2022/06/20/npc_vaccinemenstruation/","retrieved":1655766531444},{"title":"[필진 칼럼] 푸틴의 철 지난 프로파간다 “재난 배우”","contents":"2022년 6월 20일","link":"https://newspeppermint.com/2022/06/19/npc_crisisactor/","retrieved":1655680115831},{"title":"[필진 칼럼] 가상화폐의 중립성이란","contents":"2022년 6월 17일","link":"https://newspeppermint.com/2022/06/16/npc_cryptoneutrality/","retrieved":1655420987641},{"title":"[필진 칼럼] 홀푸즈의 아마존화(化)","contents":"2022년 6월 16일","link":"https://newspeppermint.com/2022/06/15/npc_wfamazonification/","retrieved":1655334554841},{"title":"[필진 칼럼] 전쟁범죄 규정과 딜레마","contents":"2022년 6월 15일","link":"https://newspeppermint.com/2022/06/14/npc_warcrime/","retrieved":1655248109047},{"title":"[필진 칼럼] 바이고렉시아: 자신의 몸에 만족하지 못하는 남자들","contents":"2022년 6월 14일","link":"https://newspeppermint.com/2022/06/13/npc_bigorexia/","retrieved":1655161764972}]}