{"title":"뉴스페퍼민트","url":"https://newspeppermint.com/","favicon":"https://newspeppermint.com/favicon.ico","elements":[{"title":"[필진 칼럼] 신냉전과 ‘인피니티 스톤’ 반도체","contents":"2022년 7월 28일","link":"https://newspeppermint.com/2022/07/27/npc_infinitystone/","retrieved":1658963346231},{"title":"[필진 칼럼] 가상화폐와 경제 불평등","contents":"2022년 7월 27일","link":"https://newspeppermint.com/2022/07/26/npc_cryptoandinequality/","retrieved":1658877015979},{"title":"[필진 칼럼] 탄수화물과 두통의 관계","contents":"2022년 7월 26일","link":"https://newspeppermint.com/2022/07/25/npc_carbsheadaches/","retrieved":1658790565126},{"title":"[필진 칼럼] 로 대 웨이드가 사라진 세상, 프로 라이프 운동의 미래는?","contents":"2022년 7월 25일","link":"https://newspeppermint.com/2022/07/24/npc_afterroevwade/","retrieved":1658704151520},{"title":"[필진 칼럼] 우크라이나 밴드 ‘칼루쉬 오케스트라’, 유로비전 2022 우승","contents":"2022년 7월 22일","link":"https://newspeppermint.com/2022/07/21/npc_eurovision2022/","retrieved":1658445046041},{"title":"[필진 칼럼] 로 대 웨이드와 과학적 사실들","contents":"2022년 7월 21일","link":"https://newspeppermint.com/2022/07/20/npc_roevwadefacts/","retrieved":1658358619284},{"title":"[필진 칼럼] 로 대 웨이드(Roe v. Wade) 파기 임박, “중간선거에 영향 없을 것”","contents":"2022년 7월 20일","link":"https://newspeppermint.com/2022/07/19/npc_roevwade2/","retrieved":1658272258806},{"title":"[필진 칼럼] 로 대 웨이드(Roe v. Wade) 파기 임박, 중간선거 뒤흔들까?","contents":"2022년 7월 19일","link":"https://newspeppermint.com/2022/07/18/npc_roevwade1/","retrieved":1658185856120},{"title":"[필진 칼럼] 항우울제의 장기적 효과에 대한 의문","contents":"2022년 7월 18일","link":"https://newspeppermint.com/2022/07/17/npc_antidepressants/","retrieved":1658099369454},{"title":"[필진 칼럼] 2022년 눈에 띄는 인구 변화들","contents":"2022년 7월 15일","link":"https://newspeppermint.com/2022/07/14/%ec%9d%b8%ea%b5%ac/","retrieved":1657840343461},{"title":"[필진 칼럼] 일론 머스크의 트위터 인수 곱씹어 보기","contents":"2022년 7월 14일","link":"https://newspeppermint.com/2022/07/13/npc_musktwitter/","retrieved":1657753761612},{"title":"[필진 칼럼] 세상을 떠나는 다른 방식","contents":"2022년 7월 13일","link":"https://newspeppermint.com/2022/07/12/npc_watercremation/","retrieved":1657667356657}]}